{
  "id": 55,
  "special": false,
  "nodes": [
    {
      "level": 0,
      "name": "낡은 검"
    },
    {
      "level": 1,
      "name": "피 묻은 검"
    },
    {
      "level": 2,
      "name": "피맺힌 검"
    },
    {
      "level": 3,
      "name": "맥동하는 피의 검"
    },
    {
      "level": 4,
      "name": "피를 갈구하는 검"
    },
    {
      "level": 5,
      "name": "주인의 피를 말리는 검"
    },
    {
      "level": 6,
      "name": "응축된 혈액의 검"
    },
    {
      "level": 7,
      "name": "혈류 제어의 검"
    },
    {
      "level": 8,
      "name": "진혈 군주의 검"
    },
    {
      "level": 9,
      "name": "영원한 혈맥의 검"
    },
    {
      "level": 10,
      "name": "진홍빛 창세의 검"
    },
    {
      "level": 11,
      "name": "카마소츠의 피의 심연 검"
    },
    {
      "level": 12,
      "name": "카마소츠의 진홍빛 절대심연 검"
    },
    {
      "level": 13,
      "name": "카마소츠의 혈월(血月) 공포 검"
    },
    {
      "level": 14,
      "name": "카마소츠의 혈월(血月) 종말군주 검"
    },
    {
      "level": 15,
      "name": "카마소츠의 혈월(血月) 신위(神威) 검"
    },
    {
      "level": 16,
      "name": "우주의 혈맥: 종언의 섭리"
    }
  ],
  "by_level": {
    "0": {
      "level": 0,
      "name": "낡은 검"
    },
    "1": {
      "level": 1,
      "name": "피 묻은 검"
    },
    "2": {
      "level": 2,
      "name": "피맺힌 검"
    },
    "3": {
      "level": 3,
      "name": "맥동하는 피의 검"
    },
    "4": {
      "level": 4,
      "name": "피를 갈구하는 검"
    },
    "5": {
      "level": 5,
      "name": "주인의 피를 말리는 검"
    },
    "6": {
      "level": 6,
      "name": "응축된 혈액의 검"
    },
    "7": {
      "level": 7,
      "name": "혈류 제어의 검"
    },
    "8": {
      "level": 8,
      "name": "진혈 군주의 검"
    },
    "9": {
      "level": 9,
      "name": "영원한 혈맥의 검"
    },
    "10": {
      "level": 10,
      "name": "진홍빛 창세의 검"
    },
    "11": {
      "level": 11,
      "name": "카마소츠의 피의 심연 검"
    },
    "12": {
      "level": 12,
      "name": "카마소츠의 진홍빛 절대심연 검"
    },
    "13": {
      "level": 13,
      "name": "카마소츠의 혈월(血月) 공포 검"
    },
    "14": {
      "level": 14,
      "name": "카마소츠의 혈월(血月) 종말군주 검"
    },
    "15": {
      "level": 15,
      "name": "카마소츠의 혈월(血月) 신위(神威) 검"
    },
    "16": {
      "level": 16,
      "name": "우주의 혈맥: 종언의 섭리"
    }
  }
}